LICENSE
setup.py
cameo_threshold/__init__.py
cameo_threshold/__main__.py
cameo_threshold/cameo_threshold.py
cameo_threshold/utils.py
cameo_threshold.egg-info/PKG-INFO
cameo_threshold.egg-info/SOURCES.txt
cameo_threshold.egg-info/dependency_links.txt
cameo_threshold.egg-info/requires.txt
cameo_threshold.egg-info/top_level.txt