Metadata-Version: 1.1
Name: cameo-threshold
Version: 0.4.0
Summary: use the copy of the original df, rather than modifying the original one
Home-page: https://github.com/bohachu/cameo_threshold
Author: JC Wang
Author-email: jcxgtcw@gmail.com
License: BSD 2-clause
Platform: UNKNOWN
Classifier: Programming Language :: Python :: 3
